LICENSE
MANIFEST.in
README.md
pypi_readme.rst
setup.py
aos/__init__.py
aos/__main__.py
aos/config.py
aos/constant.py
aos/download.py
aos/ota_upload.py
aos/util.py
aos/commands/__init__.py
aos/commands/check.py
aos/commands/create.py
aos/commands/debug.py
aos/commands/devices.py
aos/commands/install.py
aos/commands/list.py
aos/commands/make.py
aos/commands/monitor.py
aos/commands/open.py
aos/commands/ota.py
aos/commands/pack.py
aos/commands/remove.py
aos/commands/upgrade.py
aos/commands/upload.py
aos/managers/__init__.py
aos/managers/addon.py
aos/managers/constant.py
aos/managers/localpkg.py
aos/managers/metadata.py
aos/managers/misc.py
aos/managers/package.py
aos/managers/queryserver.py
aos/managers/repo.py
aos/managers/rpmfile.py
aos/managers/sqlitedb.py
aos/managers/test.py
aos/usertrace/__init__.py
aos/usertrace/do_report.py
aos/usertrace/report.py
aos_cube.egg-info/PKG-INFO
aos_cube.egg-info/SOURCES.txt
aos_cube.egg-info/dependency_links.txt
aos_cube.egg-info/entry_points.txt
aos_cube.egg-info/requires.txt
aos_cube.egg-info/top_level.txt