Metadata-Version: 1.2
Name: aos-cube
Version: 0.5.11
Summary: aos commmand line tool for AliOS-Things development.
Home-page: https://pypi.org/project/aos-cube/
Author: Alibaba
Author-email: aliosthings@service.aliyun.com
License: Apache License
